cadence/__init__.py
cadence/activity.py
cadence/activity_loop.py
cadence/activity_method.py
cadence/cadence_types.py
cadence/clock_decision_context.py
cadence/connection.py
cadence/constants.py
cadence/conversions.py
cadence/decision_loop.py
cadence/decisions.py
cadence/errors.py
cadence/exception_handling.py
cadence/exceptions.py
cadence/frames.py
cadence/ioutils.py
cadence/kvheaders.py
cadence/marker.py
cadence/replay_interceptor.py
cadence/state_machines.py
cadence/tchannel.py
cadence/thrift.py
cadence/util.py
cadence/worker.py
cadence/workerfactory.py
cadence/workflow.py
cadence/workflowservice.py
cadence/thrift/cadence.thrift
cadence/thrift/shared.thrift
cadence_client-1.0.1.dist-info/LICENSE
cadence_client-1.0.1.dist-info/METADATA
cadence_client-1.0.1.dist-info/WHEEL
cadence_client-1.0.1.dist-info/top_level.txt
cadence_client-1.0.1.dist-info/RECORD
