Metadata-Version: 2.1
Name: cadence-client
Version: 1.0.1
Summary: Python framework for Cadence Workflow Service
Home-page: https://github.com/firdaus/cadence-python
Author: Mohammed Firdaus
Author-email: firdaus.halim@gmail.com
License: UNKNOWN
Platform: UNKNOWN
Classifier: Programming Language :: Python :: 3
Classifier: Programming Language :: Python :: 3.7
Classifier: Programming Language :: Python :: 3.8
Classifier: License :: OSI Approved :: MIT License
Classifier: Operating System :: OS Independent
Requires-Dist: dataclasses-json (>=0.3.8)
Requires-Dist: more-itertools (>=7.0.0)
Requires-Dist: ply (>=3.11)
Requires-Dist: tblib (>=1.6.0)
Requires-Dist: thriftrw (>=1.7.2)
